TracGoogleStaticMapMacro-1.1.dist-info/METADATA
TracGoogleStaticMapMacro-1.1.dist-info/RECORD
TracGoogleStaticMapMacro-1.1.dist-info/WHEEL
TracGoogleStaticMapMacro-1.1.dist-info/entry_points.txt
TracGoogleStaticMapMacro-1.1.dist-info/top_level.txt
tracgooglestaticmap/__init__.py
tracgooglestaticmap/macro.py
